chain_guardrail/main.py
chain_guardrail/bias/gender.py
chain_guardrail/pii/presidio_pii.py
chain_guardrail/profanity/bad_words_list.py
chain_guardrail/profanity/fixed_pattern.py
chain_guardrail/toxicity/large.py
chain_guardrail-0.0.12.dist-info/LICENSE
chain_guardrail-0.0.12.dist-info/METADATA
chain_guardrail-0.0.12.dist-info/WHEEL
chain_guardrail-0.0.12.dist-info/top_level.txt
chain_guardrail-0.0.12.dist-info/RECORD
