Metadata-Version: 2.1
Name: chain_guardrail
Version: 0.0.12
Summary: Guardrails compatible with Langchan=in's LCEL
Author-email: Shubham Gupta <shubham.mdsk@gmail.com>
Project-URL: Homepage, https://github.com/shubh1204/chain-guardrail.git
Classifier: Programming Language :: Python :: 3
Classifier: License :: OSI Approved :: MIT License
Classifier: Operating System :: OS Independent
Requires-Python: >=3.8
License-File: LICENSE
Requires-Dist: presidio-analyzer ==2.2.354
Requires-Dist: presidio-anonymizer ==2.2.354
Requires-Dist: spacy-transformers ==1.3.5
Requires-Dist: transformers
Requires-Dist: torch
